neurosystems/__init__.py
neurosystems/neurosystems.py
neurosystems-0.0.3.dist-info/LICENSE
neurosystems-0.0.3.dist-info/METADATA
neurosystems-0.0.3.dist-info/WHEEL
neurosystems-0.0.3.dist-info/top_level.txt
neurosystems-0.0.3.dist-info/RECORD
