Metadata-Version: 2.1
Name: neurosystems
Version: 0.0.3
Summary: A package containing all Neurosistemas Lab's codes
Home-page: https://github.com/Neurosistemas-Lab/neurosystems
Author: Laboratorio de Neurosistemas
Author-email: is.jaras@gmail.com
License: UNKNOWN
Platform: UNKNOWN
Classifier: Programming Language :: Python :: 3.7
Classifier: License :: OSI Approved :: GNU General Public License v3 (GPLv3)
Requires-Dist: ipython (>=6)
Requires-Dist: nbformat (>=4)
Requires-Dist: nbconvert (>=5)
Requires-Dist: requests (>=2)
